<?xml version="1.0"?>
<definitions>
	<definition>
		<key>heading_title</key>
		<value><![CDATA[Poplatok za malú objednávku]]></value>
	</definition>
	<definition>
		<key>total_name</key>
		<value><![CDATA[Poplatok za malú objednávku]]></value>
	</definition>
	<definition>
		<key>text_total</key>
		<value><![CDATA[Celkové sumy objednávok]]></value>
	</definition>
	<definition>
		<key>text_success</key>
		<value><![CDATA[Úspech: upravili ste celkový poplatok za nízku objednávku!]]></value>
	</definition>
	<definition>
		<key>entry_total</key>
		<value><![CDATA[Celková suma objednávky:]]></value>
	</definition>
	<definition>
		<key>entry_fee</key>
		<value><![CDATA[Poplatok:]]></value>
	</definition>
	<definition>
		<key>entry_tax</key>
		<value><![CDATA[Daňová trieda:]]></value>
	</definition>
	<definition>
		<key>entry_status</key>
		<value><![CDATA[Stav:]]></value>
	</definition>
	<definition>
		<key>entry_sort_order</key>
		<value><![CDATA[Poradie zoradenia:]]></value>
	</definition>
	<definition>
		<key>entry_calculation_order</key>
		<value><![CDATA[Poradie výpočtu:]]></value>
	</definition>
	<definition>
		<key>error_permission</key>
		<value><![CDATA[Upozornenie: Nemáte oprávnenie upravovať celkový poplatok za nízku objednávku!]]></value>
	</definition>
</definitions>
