<?xml version="1.0"?>
<definitions>
	<definition>
		<key>default_weight_name</key>
		<value><![CDATA[Přeprava podle hmotnosti]]></value>
	</definition>
	<definition>
		<key>text_shipping</key>
		<value><![CDATA[Doprava]]></value>
	</definition>
	<definition>
		<key>text_additional_settings</key>
		<value><![CDATA[ Další nastavení ]]></value>
	</definition>
	<definition>
		<key>text_success</key>
		<value><![CDATA[Úspěch: Upravili jste dopravu podle hmotnosti!]]></value>
	</definition>
	<definition>
		<key>entry_rate</key>
		<value><![CDATA[Sazby: <br/><span class="help">Příklad: 5:10,00,7:12,00 Hmotnost:Cena, Hmotnost:Cena atd. V tomto příkladu 5 liber = 10,00 $. Kde libra je vaše hmotnostní třída obchodu a $ je základní měna obchodu. Obojí můžete změnit v Nastavení obchodu</span>]]></value>
	</definition>
	<definition>
		<key>entry_status</key>
		<value><![CDATA[Postavení:]]></value>
	</definition>
	<definition>
		<key>entry_tax</key>
		<value><![CDATA[Daňová třída:]]></value>
	</definition>
	<definition>
		<key>entry_location</key>
		<value><![CDATA[Umístění:]]></value>
	</definition>
	<definition>
		<key>entry_sort_order</key>
		<value><![CDATA[Pořadí řazení:]]></value>
	</definition>
	<definition>
		<key>error_permission</key>
		<value><![CDATA[Upozornění: Nemáte oprávnění upravovat zásilku na základě hmotnosti!]]></value>
	</definition>
	<definition>
		<key>example_weight_text</key>
		<value><![CDATA[Hmotnost: ]]></value>
	</definition>
	<definition>
		<key>example_currency_text</key>
		<value><![CDATA[Měna: ]]></value>
	</definition>
</definitions>
