<?xml version="1.0"?>
<definitions>
	<definition>
		<key>heading_title</key>
		<value><![CDATA[Specialerbjudanden]]></value>
	</definition>
	<definition>
		<key>text_empty</key>
		<value><![CDATA[Det finns inga produkter med specialerbjudanden att lista.]]></value>
	</definition>
	<definition>
		<key>text_stars</key>
		<value><![CDATA[%s av 5 stjärnor!]]></value>
	</definition>
	<definition>
		<key>text_sort</key>
		<value><![CDATA[Sortera efter:]]></value>
	</definition>
	<definition>
		<key>text_default</key>
		<value><![CDATA[Standard]]></value>
	</definition>
	<definition>
		<key>text_name_asc</key>
		<value><![CDATA[Namn A - Z]]></value>
	</definition>
	<definition>
		<key>text_name_desc</key>
		<value><![CDATA[Namn Z - A]]></value>
	</definition>
	<definition>
		<key>text_price_asc</key>
		<value><![CDATA[Pris Lågt > Högt]]></value>
	</definition>
	<definition>
		<key>text_price_desc</key>
		<value><![CDATA[Pris Hög > Låg]]></value>
	</definition>
	<definition>
		<key>text_rating_asc</key>
		<value><![CDATA[Lägsta betyg]]></value>
	</definition>
	<definition>
		<key>text_rating_desc</key>
		<value><![CDATA[Högsta betyg]]></value>
	</definition>
</definitions>
