<?xml version="1.0"?>
<definitions>
	<definition>
		<key>heading_title</key>
		<value><![CDATA[Groupes d’utilisateurs]]></value>
	</definition>
	<definition>
		<key>text_group</key>
		<value><![CDATA[Groupe d’utilisateurs]]></value>
	</definition>
	<definition>
		<key>text_success</key>
		<value><![CDATA[Succès : Vous avez modifié les groupes d’utilisateurs !]]></value>
	</definition>
	<definition>
		<key>text_success_group_added</key>
		<value><![CDATA[Succès : Vous avez créé le groupe d’utilisateurs avec succès !]]></value>
	</definition>
	<definition>
		<key>text_go_to_page</key>
		<value><![CDATA[Aller à la page]]></value>
	</definition>
	<definition>
		<key>text_delete_confirm</key>
		<value><![CDATA[Supprimer le groupe d’utilisateurs ?]]></value>
	</definition>
	<definition>
		<key>column_name</key>
		<value><![CDATA[Nom du groupe d’utilisateurs]]></value>
	</definition>
	<definition>
		<key>column_action</key>
		<value><![CDATA[Action]]></value>
	</definition>
	<definition>
		<key>entry_name</key>
		<value><![CDATA[Nom du groupe d’utilisateurs :]]></value>
	</definition>
	<definition>
		<key>column_controller</key>
		<value><![CDATA[Contrôleur]]></value>
	</definition>
	<definition>
		<key>column_access</key>
		<value><![CDATA[Accès]]></value>
	</definition>
	<definition>
		<key>column_modify</key>
		<value><![CDATA[Modifier]]></value>
	</definition>
	<definition>
		<key>error_permission</key>
		<value><![CDATA[Attention : Vous n’avez pas la permission de modifier les groupes d’utilisateurs !]]></value>
	</definition>
	<definition>
		<key>error_name</key>
		<value><![CDATA[Le nom du groupe d’utilisateurs doit être compris entre 2 et 64 caractères !]]></value>
	</definition>
	<definition>
		<key>error_user</key>
		<value><![CDATA[Attention : Ce groupe d’utilisateurs ne peut pas être supprimé car il est actuellement attribué à %s utilisateurs !]]></value>
	</definition>
</definitions>
