<?xml version="1.0"?>
<definitions>
	<definition>
		<key>default_cheque_name</key>
		<value><![CDATA[Šek / Peňažný poukaz]]></value>
	</definition>
	<definition>
		<key>text_payment</key>
		<value><![CDATA[Platba]]></value>
	</definition>
	<definition>
		<key>text_success</key>
		<value><![CDATA[Úspech: upravili ste údaje účtu šeku / poštového poukazu!]]></value>
	</definition>
	<definition>
		<key>default_cheque_payable</key>
		<value><![CDATA[Vyplatiť na:<br /><span class="help">Uveďte meno, na ktoré má byť šek vystavený</span>]]></value>
	</definition>
	<definition>
		<key>default_cheque_address</key>
		<value><![CDATA[Poslať poštou alebo zaslať na:<br /><span class="help">Uveďte adresu, kam odoslať šek. Ak je prázdne, použije sa adresa hlavného obchodu.</span>]]></value>
	</definition>
	<definition>
		<key>default_cheque_order_status_id</key>
		<value><![CDATA[Stav objednávky:]]></value>
	</definition>
	<definition>
		<key>default_cheque_location_id</key>
		<value><![CDATA[Umiestnenie:]]></value>
	</definition>
	<definition>
		<key>default_cheque_location_id_0</key>
		<value><![CDATA[Všetky lokality]]></value>
	</definition>
	<definition>
		<key>error_permission</key>
		<value><![CDATA[Varovanie: Nemáte oprávnenie upravovať platobný šek / poštový poukaz!]]></value>
	</definition>
	<definition>
		<key>error_payable</key>
		<value><![CDATA[Príjemca platby je povinný!]]></value>
	</definition>
</definitions>
