<?xml version="1.0"?>
<definitions>
	<definition>
		<key>text_title</key>
		<value><![CDATA[Fedex]]></value>
	</definition>
	<definition>
		<key>text_description</key>
		<value><![CDATA[Fedex]]></value>
	</definition>
	<definition>
		<key>fedex_error_empty_postcode</key>
		<value><![CDATA[Hiba: üres irányítószám.]]></value>
	</definition>
	<definition>
		<key>fedex_error_no_service</key>
		<value><![CDATA[A szolgáltatás nem érhető el az Ön területén. Ellenőrizze, hogy a szállítási címe helyes-e.]]></value>
	</definition>
</definitions>
