<?xml version="1.0"?>
<definitions>
	<definition>
		<key>heading_title</key>
		<value><![CDATA[Κλάσεις φόρου]]></value>
	</definition>
	<definition>
		<key>text_class</key>
		<value><![CDATA[Κατηγορία Φόρου]]></value>
	</definition>
	<definition>
		<key>text_rate</key>
		<value><![CDATA[Φορολογικός Συντελεστής]]></value>
	</definition>
	<definition>
		<key>text_success</key>
		<value><![CDATA[Επιτυχία: Έχετε τροποποιήσει τις φορολογικές κλάσεις!]]></value>
	</definition>
	<definition>
		<key>column_title</key>
		<value><![CDATA[Τίτλος Φορολογικής Κατηγορίας]]></value>
	</definition>
	<definition>
		<key>column_action</key>
		<value><![CDATA[Δράση]]></value>
	</definition>
	<definition>
		<key>tab_details</key>
		<value><![CDATA[Λεπτομέρειες]]></value>
	</definition>
	<definition>
		<key>tab_rates</key>
		<value><![CDATA[Τιμές]]></value>
	</definition>
	<definition>
		<key>entry_title</key>
		<value><![CDATA[Τίτλος Κατηγορίας Φόρου:]]></value>
	</definition>
	<definition>
		<key>entry_description</key>
		<value><![CDATA[Περιγραφή ορατή στους πελάτες]]></value>
	</definition>
	<definition>
		<key>entry_location</key>
		<value><![CDATA[Τοποθεσία]]></value>
	</definition>
	<definition>
		<key>entry_zone</key>
		<value><![CDATA[Ζώνη τοποθεσίας]]></value>
	</definition>
	<definition>
		<key>entry_priority</key>
		<value><![CDATA[Προτεραιότητα]]></value>
	</definition>
	<definition>
		<key>entry_rate</key>
		<value><![CDATA[Φορολογικός συντελεστής]]></value>
	</definition>
	<definition>
		<key>error_permission</key>
		<value><![CDATA[Προειδοποίηση: Δεν έχετε άδεια να τροποποιήσετε τις κατηγορίες φόρων!]]></value>
	</definition>
	<definition>
		<key>error_tax_title</key>
		<value><![CDATA[Ο τίτλος φορολογικής κατηγορίας πρέπει να έχει μήκος μεταξύ 2 και 32 χαρακτήρων!]]></value>
	</definition>
	<definition>
		<key>error_rate</key>
		<value><![CDATA[Απαιτείται συντελεστής φόρου!]]></value>
	</definition>
	<definition>
		<key>error_product</key>
		<value><![CDATA[Προειδοποίηση: Αυτή η κατηγορία φόρου δεν μπορεί να διαγραφεί καθώς είναι επί του παρόντος εκχωρημένη σε %s προϊόντα!]]></value>
	</definition>
	<definition>
		<key>text_tax_all_zones</key>
		<value><![CDATA[όλες οι ζώνες τοποθεσίας]]></value>
	</definition>
	<definition>
		<key>entry_tax_rate_threshold</key>
		<value><![CDATA[Εφαρμόστε φόρο αν<br /><span class="help">Εφαρμόστε αυτόν τον φόρο μόνο αν το φορολογητέο ποσό (προϊόν, αποστολή, υποσύνολο, κ.λπ.) είναι …</span>]]></value>
	</definition>
	<definition>
		<key>entry_tax_exempt_groups</key>
		<value><![CDATA[Ομάδες απαλλαγής φόρου<br /><span class="help">Επιλέξτε ομάδες πελατών για απαλλαγή από αυτόν τον φόρο</span>]]></value>
	</definition>
	<definition>
		<key>text_absolute</key>
		<value><![CDATA[Απόλυτο]]></value>
	</definition>
	<definition>
		<key>text_percent</key>
		<value><![CDATA[Ποσοστό]]></value>
	</definition>
</definitions>
