<?xml version="1.0"?>
<definitions>
	<definition>
		<key>default_per_item_shipping_name</key>
		<value><![CDATA[Per articolo]]></value>
	</definition>
	<definition>
		<key>text_shipping</key>
		<value><![CDATA[Spedizione]]></value>
	</definition>
	<definition>
		<key>text_success</key>
		<value><![CDATA[Successo: hai modificato le tariffe di spedizione per articolo!]]></value>
	</definition>
	<definition>
		<key>default_per_item_shipping_cost</key>
		<value><![CDATA[Costo:]]></value>
	</definition>
	<definition>
		<key>default_per_item_shipping_tax</key>
		<value><![CDATA[Classe di imposta:]]></value>
	</definition>
	<definition>
		<key>default_per_item_shipping_tax_0</key>
		<value><![CDATA[---Nessuno---]]></value>
	</definition>
	<definition>
		<key>default_per_item_shipping_location_id</key>
		<value><![CDATA[Posizione:]]></value>
	</definition>
	<definition>
		<key>default_per_item_shipping_location_id_0</key>
		<value><![CDATA[Tutte le località]]></value>
	</definition>
	<definition>
		<key>error_permission</key>
		<value><![CDATA[Avviso: Non hai il permesso di modificare le tariffe di spedizione per articolo!]]></value>
	</definition>
</definitions>
