<?xml version="1.0"?>
<definitions>
	<definition>
		<key>heading_title</key>
		<value><![CDATA[Twoje konto zostało utworzone!]]></value>
	</definition>
	<definition>
		<key>text_message</key>
		<value><![CDATA[<p>Gratulacje! Twoje nowe konto zostało pomyślnie utworzone!</p>
<p>Teraz możesz skorzystać z uprawnień członkowskich, aby wzbogacić swoje doświadczenie zakupów online w naszym sklepie.</p>
<p>Jeśli masz DOWOLNE pytania dotyczące działania tego sklepu internetowego, wyślij e-mail do właściciela sklepu.</p>
<p>Potwierdzenie zostało wysłane na podany adres e-mail. Jeśli nie otrzymasz go w ciągu godziny, prosimy <a href="%s">skontaktuj się z nami</a>.</p>]]></value>
	</definition>
	<definition>
		<key>text_approval</key>
		<value><![CDATA[<p>Dziękujemy za rejestrację w %s!</p><p>Zostaniesz powiadomiony e-mailem, gdy Twoje konto zostanie aktywowane przez właściciela sklepu.</p><p>Jeśli masz jakiekolwiek pytania dotyczące działania tego sklepu internetowego, prosimy <a href="%s">skontaktować się z właścicielem sklepu</a>.</p>]]></value>
	</definition>
	<definition>
		<key>heading_title_activation</key>
		<value><![CDATA[Twoje konto zostało utworzone, ale wymagana jest aktywacja. Proszę postępować zgodnie z instrukcjami.]]></value>
	</definition>
	<definition>
		<key>text_activate</key>
		<value><![CDATA[<p>Dziękujemy za rejestrację w %s!</p><p>Otrzymasz powiadomienie e-mailem zawierające instrukcje aktywacji konta. Musisz kliknąć link podany w wiadomości e-mail, aby aktywować konto. Jeśli nie otrzymasz wiadomości, sprawdź foldery spamu lub niechcianej poczty.</p><p>Jeśli masz JAKIEKOLWIEK pytania dotyczące działania tego sklepu internetowego, prosimy o <a href="%s">kontakt z właścicielem sklepu</a>.</p>]]></value>
	</definition>
	<definition>
		<key>text_account</key>
		<value><![CDATA[Konto]]></value>
	</definition>
	<definition>
		<key>text_success</key>
		<value><![CDATA[Sukces]]></value>
	</definition>
</definitions>
